Privacify/__init__.py
Privacify/main.py
data_anonymizer/__init__.py
data_anonymizer/main.py
privacify-0.3.4.dist-info/METADATA
privacify-0.3.4.dist-info/WHEEL
privacify-0.3.4.dist-info/top_level.txt
privacify-0.3.4.dist-info/RECORD
