Metadata-Version: 2.4
Name: privacify
Version: 0.3.4
Summary: A package to anonymize sensitive data in text.
Author: Ashour Merza
Classifier: Programming Language :: Python :: 3
Classifier: License :: OSI Approved :: MIT License
Classifier: Operating System :: OS Independent
Requires-Python: >=3.6
Dynamic: author
Dynamic: classifier
Dynamic: description
Dynamic: description-content-type
Dynamic: requires-python
Dynamic: summary
